navutils/__init__.py
navutils/__version__.py
navutils/apps.py
navutils/breadcrumbs.py
navutils/context_processors.py
navutils/menu.py
navutils/mixins.py
navutils/settings.py
navutils/views.py
navutils/templates/navutils/breadcrumbs.html
navutils/templates/navutils/crumb.html
navutils/templates/navutils/menu.html
navutils/templates/navutils/node.html
navutils/templatetags/__init__.py
navutils/templatetags/navutils_tags.py
tests/__init__.py
tests/test_breadcrumbs.py
tests/test_menu.py
tests/test_mixins.py
tests/test_render_nested.py
tests/test_app/__init__.py
tests/test_app/models.py
tests/test_app/urls.py
tests/test_app/views.py
django_navutils-0.8.dist-info/LICENSE
django_navutils-0.8.dist-info/METADATA
django_navutils-0.8.dist-info/WHEEL
django_navutils-0.8.dist-info/top_level.txt
django_navutils-0.8.dist-info/RECORD
