Metadata-Version: 2.1
Name: django-navutils
Version: 0.8
Summary: A lightweight package for handling menus and breadcrumbs in your django project
Home-page: http://github.com/AgateBlue/django-navutils
Author: Agate Blue
Author-email: me@agate.blue
Maintainer: Agate Blue
Maintainer-email: me@agate.blue
License: BSD License
Platform: any
Classifier: Development Status :: 4 - Beta
Classifier: Environment :: Web Environment
Classifier: Framework :: Django
Classifier: Intended Audience :: Developers
Classifier: License :: OSI Approved :: BSD License
Classifier: Operating System :: OS Independent
Classifier: Programming Language :: Python
Classifier: Programming Language :: Python :: 3
Classifier: Framework :: Django :: 3.2
Classifier: Topic :: Utilities
Requires-Dist: persisting-theory
